README.md
setup.cfg
setup.py
linedit/__init__.py
linedit.egg-info/PKG-INFO
linedit.egg-info/SOURCES.txt
linedit.egg-info/dependency_links.txt
linedit.egg-info/not-zip-safe
linedit.egg-info/top_level.txt