Metadata-Version: 1.1
Name: linedit
Version: 1.1
Summary: Simple Interface to Edit specific lines in files.
Home-page: https://github.com/colathro/linedit
Author: colathro
Author-email: colathro@microsoft.com
License: MIT
Download-URL: https://github.com/colathro/linedit/archive/1.1.tar.gz
Platform: UNKNOWN
